django_iitg_auth-0.0.4.dist-info/DESCRIPTION.rst
django_iitg_auth-0.0.4.dist-info/METADATA
django_iitg_auth-0.0.4.dist-info/RECORD
django_iitg_auth-0.0.4.dist-info/WHEEL
django_iitg_auth-0.0.4.dist-info/metadata.json
django_iitg_auth-0.0.4.dist-info/top_level.txt
iitgauth/__init__.py
iitgauth/apps.py
iitgauth/auth.py
iitgauth/constants.py
iitgauth/forms.py
iitgauth/tests.py
iitgauth/views.py
