Metadata-Version: 2.0
Name: django-iitg-auth
Version: 0.0.4
Summary: ``django-iitg-auth`` is a reusable Django application which provides a custom authencation backend for authenticating with IIT Guwahati webmail servers, a login form and a utility view.
Home-page: https://github.com/narenchoudhary/django-iitg-auth
Author: Narendra Choudhary
Author-email: narendralegha.mail@gmail.com
License: BSD 3-Clause
Keywords: django library development authentication
Platform: UNKNOWN
Classifier: Development Status :: 3 - Alpha
Classifier: Environment :: Web Environment
Classifier: Framework :: Django
Classifier: Framework :: Django :: 1.8
Classifier: Framework :: Django :: 1.9
Classifier: Framework :: Django :: 1.10
Classifier: Intended Audience :: Developers
Classifier: License :: OSI Approved :: BSD License
Classifier: Natural Language :: English
Classifier: Operating System :: OS Independent
Classifier: Programming Language :: Python
Classifier: Programming Language :: Python :: 2
Classifier: Programming Language :: Python :: 2.7
Classifier: Programming Language :: Python :: 3.3
Classifier: Programming Language :: Python :: 3.4
Classifier: Programming Language :: Python :: 3.5
Classifier: Topic :: Internet :: WWW/HTTP
Classifier: Topic :: Software Development :: Libraries :: Python Modules
Requires-Dist: Django (>=1.7)
